jicson/__init__.py
jicson/jicson.py
jicson-1.0.2.dist-info/METADATA
jicson-1.0.2.dist-info/WHEEL
jicson-1.0.2.dist-info/top_level.txt
jicson-1.0.2.dist-info/RECORD
