Metadata-Version: 2.1
Name: jicson
Version: 1.0.2
Summary: Easy ics file parser
Home-page: http://caly.io
Author: jspiner
Author-email: jspiner@naver.com
License: UNKNOWN
Keywords: ICS iCalendar JSon calendar caldav
Platform: UNKNOWN
Classifier: Development Status :: 2 - Pre-Alpha
Classifier: Topic :: Software Development :: Libraries
Classifier: Programming Language :: Python :: 2
Classifier: Programming Language :: Python :: 2.6
Classifier: Programming Language :: Python :: 2.7
Classifier: Programming Language :: Python :: 3
Classifier: Programming Language :: Python :: 3.4
Classifier: Programming Language :: Python :: 3.5
Classifier: Programming Language :: Python :: 3.6
